unicornsdk/__init__.py
unicornsdk/exceptions.py
unicornsdk/sdk.py
unicornsdk/session.py
unicornsdk/tls_session.py
unicornsdk/utils.py
unicornsdk/api/__init__.py
unicornsdk/api/baseapi.py
unicornsdk/api/captcha.py
unicornsdk/api/devicesession.py
unicornsdk/api/kasada.py
unicornsdk/api/tls.py
unicornsdk_async/__init__.py
unicornsdk_async/sdk.py
unicornsdk_async/api/__init__.py
unicornsdk_async/api/captcha.py
unicornsdk_async/api/devicesession.py
unicornsdk_async/api/kasada.py
unicornsdk_async/api/tls.py
unicorn_sdk-0.0.16.dist-info/METADATA
unicorn_sdk-0.0.16.dist-info/WHEEL
unicorn_sdk-0.0.16.dist-info/top_level.txt
unicorn_sdk-0.0.16.dist-info/RECORD
