Metadata-Version: 2.1
Name: unicorn-sdk
Version: 0.0.16
Summary: Python Sdk for UnicornAIO API
Project-URL: homepage, https://www.unicorn-bot.com/
Project-URL: repository, https://github.com/unicorn-aio/unicorn-sdk
Requires-Python: >=3.7
Requires-Dist: requests
Requires-Dist: brotli
Requires-Dist: loguru
Requires-Dist: httpx
Requires-Dist: aiohttp
Requires-Dist: tenacity
